baguette/__init__.py
baguette/app.py
baguette/config.py
baguette/converters.py
baguette/forms.py
baguette/headers.py
baguette/httpexceptions.py
baguette/json.py
baguette/middleware.py
baguette/rendering.py
baguette/request.py
baguette/responses.py
baguette/router.py
baguette/testing.py
baguette/types.py
baguette/utils.py
baguette/view.py
baguette/middlewares/__init__.py
baguette/middlewares/default_headers.py
baguette/middlewares/errors.py
baguette-0.3.1.dist-info/LICENSE
baguette-0.3.1.dist-info/METADATA
baguette-0.3.1.dist-info/WHEEL
baguette-0.3.1.dist-info/top_level.txt
baguette-0.3.1.dist-info/RECORD
