Metadata-Version: 2.1
Name: baguette
Version: 0.3.1
Summary: Asynchronous web framework.
Home-page: https://github.com/takos22/baguette
Author: takos22
Author-email: takos2210@gmail.com
License: MIT
Project-URL: Documentation, https://baguette.readthedocs.io/
Project-URL: Issue tracker, https://github.com/takos22/baguette/issues
Platform: UNKNOWN
Classifier: Development Status :: 3 - Alpha
Classifier: Environment :: Web Environment
Classifier: Intended Audience :: Developers
Classifier: License :: OSI Approved :: MIT License
Classifier: Operating System :: OS Independent
Classifier: Topic :: Internet :: WWW/HTTP
Classifier: Programming Language :: Python
Classifier: Programming Language :: Python :: 3
Classifier: Programming Language :: Python :: 3 :: Only
Classifier: Programming Language :: Python :: 3.6
Classifier: Programming Language :: Python :: 3.7
Classifier: Programming Language :: Python :: 3.8
Classifier: Programming Language :: Python :: 3.9
Requires-Python: >=3.6
Requires-Dist: aiofiles
Requires-Dist: cachetools
Requires-Dist: jinja2
Requires-Dist: ujson
Provides-Extra: uvicorn
Requires-Dist: uvicorn[standard] ; extra == 'uvicorn'
